udc/__init__.py
udc/benchling/__init__.py
udc/benchling/entry.py
udc/benchling/resource.py
udc/benchling/root.py
udc/benchling/schema.py
udc/benchling/sequence.py
udc/cli.yaml
udc/main.py
udc/py.typed
udc/quilt/__init__.py
udc/quilt/resource.py
udc/types.py
udc/wrapper.py
udc-0.3.3.dist-info/LICENSE
udc-0.3.3.dist-info/METADATA
udc-0.3.3.dist-info/WHEEL
udc-0.3.3.dist-info/entry_points.txt
udc-0.3.3.dist-info/RECORD
