Metadata-Version: 2.1
Name: udc
Version: 0.3.3
Summary: The Universal Data Client command-line tool
Author: Ernest Prabhakar
Author-email: ernest@quiltdata.io
Requires-Python: >=3.10,<4.0
Classifier: Programming Language :: Python :: 3
Classifier: Programming Language :: Python :: 3.10
Classifier: Programming Language :: Python :: 3.11
Requires-Dist: anyio (>=3.7.0,<4.0.0)
Requires-Dist: asyncclick (>=8.1.3.4,<9.0.0.0)
Requires-Dist: benchling-sdk (>=1.6.1,<2.0.0)
Requires-Dist: quilt3 (>=5.3.1,<6.0.0)
Requires-Dist: quiltplus (>=0.9.3)
Requires-Dist: trio (>=0.22.0,<0.23.0)
Requires-Dist: typing-extensions (>=4.5.0,<5.0.0)
Requires-Dist: un-yaml (>=0.3.1)
Requires-Dist: urllib3 (<2)
